dokman/__init__.py
dokman/cli/__init__.py
dokman/cli/app.py
dokman/cli/commands/__init__.py
dokman/cli/commands/backup.py
dokman/cli/commands/config.py
dokman/cli/commands/debug.py
dokman/cli/commands/lifecycle.py
dokman/cli/commands/maintenance.py
dokman/cli/commands/project.py
dokman/cli/commands/resources.py
dokman/cli/formatter.py
dokman/cli/helpers.py
dokman/clients/__init__.py
dokman/clients/compose_client.py
dokman/clients/docker_client.py
dokman/exceptions.py
dokman/models/__init__.py
dokman/models/backup.py
dokman/models/diff.py
dokman/models/enums.py
dokman/models/project.py
dokman/models/resources.py
dokman/models/results.py
dokman/services/__init__.py
dokman/services/config_manager.py
dokman/services/project_manager.py
dokman/services/resource_manager.py
dokman/services/service_manager.py
dokman/services/version_checker.py
dokman/storage/__init__.py
dokman/storage/registry.py
dokman-0.3.2.dist-info/WHEEL
dokman-0.3.2.dist-info/entry_points.txt
dokman-0.3.2.dist-info/METADATA
dokman-0.3.2.dist-info/RECORD
