Metadata-Version: 2.3
Name: dokman
Version: 0.3.2
Summary: Centralized Docker Compose deployment management CLI
Requires-Dist: typer>=0.20.1
Requires-Dist: docker>=7.0.0
Requires-Dist: rich>=13.0.0
Requires-Dist: packaging>=24.0
Requires-Python: >=3.13
Project-URL: Bug Tracker, https://github.com/Alg0rix/dokman/issues
Project-URL: Changelog, https://github.com/Alg0rix/dokman/releases
Project-URL: Documentation, https://github.com/Alg0rix/dokman#readme
Project-URL: Homepage, https://github.com/Alg0rix/dokman
Project-URL: Repository, https://github.com/Alg0rix/dokman
Project-URL: Source Code, https://github.com/Alg0rix/dokman
